tree_stat/__init__.py
tree_stat/__main__.py
tree_stat/_display_file_size.py
tree_stat/directory_measure.py
tree_stat/templates/tree_stat.md
tree_stat-0.2.0.dist-info/METADATA
tree_stat-0.2.0.dist-info/WHEEL
tree_stat-0.2.0.dist-info/entry_points.txt
tree_stat-0.2.0.dist-info/top_level.txt
tree_stat-0.2.0.dist-info/RECORD
