Metadata-Version: 2.1
Name: tree-stat
Version: 0.2.0
Summary: CLI script to measure the volume of a directory tree
Home-page: UNKNOWN
Author: Adrien Horgnies
Author-email: adrien.pierre.horgnies@gmail.com
License: UNKNOWN
Platform: UNKNOWN
Classifier: Programming Language :: Python :: 3
Classifier: Programming Language :: Python :: 3.5
Classifier: Programming Language :: Python :: 3.6
Classifier: Programming Language :: Python :: 3.7
Classifier: Operating System :: OS Independent
Classifier: Development Status :: 3 - Alpha
Requires-Dist: Jinja2
Provides-Extra: dev
Requires-Dist: pytest ; extra == 'dev'
